ipyrust/__init__.py
ipyrust/__main__.py
ipyrust-0.0.1.data/data/share/jupyter/kernels/ipyrust/kernel.json
ipyrust-0.0.1.dist-info/METADATA
ipyrust-0.0.1.dist-info/WHEEL
ipyrust-0.0.1.dist-info/licenses/LICENSE
ipyrust-0.0.1.dist-info/RECORD
