Metadata-Version: 2.1
Name: ipyrust
Version: 0.0.1
Summary: Simple jupyter kernel for Rust in pure python!
Project-URL: Homepage, https://github.com/lucafabbian/ipyrust
Project-URL: Bug Tracker, https://github.com/lucafabbian/ipyrust/issues
Author-email: Luca Fabbian <luca.fabbian.1999@gmail.com>
License-File: LICENSE
Classifier: License :: OSI Approved :: MIT License
Classifier: Operating System :: OS Independent
Classifier: Programming Language :: Python :: 3
Requires-Python: >=3.6
Requires-Dist: ipykernel>=6
